PyQt5/Qt5/qml/soloman/SVideo.qml
PyQt5/Qt5/qml/soloman/qmldir
PyQt6/Qt6/qml/soloman/SVideo.qml
PyQt6/Qt6/qml/soloman/qmldir
PySide2/qml/soloman/SVideo.qml
PySide2/qml/soloman/qmldir
PySide6/qml/soloman/SVideo.qml
PySide6/qml/soloman/qmldir
soloman/__init__.py
soloman/fps_clocks.py
soloman/misc.py
soloman/pyqt_inter_audio.py
soloman/pyqt_inter_video.py
soloman/audio/__init__.py
soloman/video/__init__.py
soloman-3.1.1.dist-info/LICENSE
soloman-3.1.1.dist-info/METADATA
soloman-3.1.1.dist-info/WHEEL
soloman-3.1.1.dist-info/top_level.txt
soloman-3.1.1.dist-info/RECORD
