Metadata-Version: 2.1
Name: soloman
Version: 3.1.1
Summary: For the love of Artificial Intelligence, Python and QML
Home-page: https://github.com/deuteronomy-works/soloman
Author: Amoh - Gyebi Godwin Ampofo Michael
Author-email: amohgyebigodwin@gmail.com
License: UNKNOWN
Project-URL: Bug Tracker, https://github.com/deuteronomy-works/soloman/issues/
Project-URL: Documentation, https://github.com/deuteronomy-works/soloman/wiki/
Project-URL: Source Code, https://github.com/deuteronomy-works/soloman/
Keywords: audio,pyaudio,ffmpeg,qml,pyffmpeg
Platform: UNKNOWN
Classifier: Programming Language :: Python
Classifier: Programming Language :: Python :: 3
Classifier: Development Status :: 4 - Beta
Classifier: Environment :: Other Environment
Classifier: Intended Audience :: Developers
Classifier: License :: OSI Approved :: MIT License
Classifier: Operating System :: OS Independent
Classifier: Topic :: Software Development :: Libraries :: Python Modules
License-File: LICENSE
Requires-Dist: numpy
Requires-Dist: QtPy
Requires-Dist: pyffmpeg
